ngsscriptlibrary/__init__.py
ngsscriptlibrary/annotation.py
ngsscriptlibrary/barcodes.py
ngsscriptlibrary/mosaic.py
ngsscriptlibrary/parsing.py
ngsscriptlibrary/pipeline_db.py
ngsscriptlibrary/targets.py
ngsscriptlibrary/docs/DL_doublescores.csv
ngsscriptlibrary/docs/DL_singlescores.csv
ngsscriptlibrary/docs/adaptercodes.txt
ngsscriptlibrary/docs/adapters.txt
ngsscriptlibrary/docs/barcodehussle.txt
ngsscriptlibrary/docs/picardheader.txt
ngsscriptlibrary/docs/snpcheck.csv
ngsscriptlibrary/docs/so_literature_vars.csv
ngsscriptlibrary-1.1.0.dist-info/LICENSE.md
ngsscriptlibrary-1.1.0.dist-info/METADATA
ngsscriptlibrary-1.1.0.dist-info/WHEEL
ngsscriptlibrary-1.1.0.dist-info/top_level.txt
ngsscriptlibrary-1.1.0.dist-info/RECORD
