Metadata-Version: 2.1
Name: ngsscriptlibrary
Version: 1.1.0
Summary: Scripts for NGS data-analysis
Home-page: https://www.github.com/martinhaagmans/ngsscriptlibrary
Author: Martin Haagmans
Author-email: mahaagmans@gmail.com
License: MIT
Platform: UNKNOWN
Requires-Dist: PyMySQL (>=0.8.1)
Requires-Dist: pybedtools (>=0.7.10)
Requires-Dist: PyVCF (>=0.6.8)
Requires-Dist: pysam (>=0.14.1)
Requires-Dist: pandas (>=0.23.0)
Requires-Dist: seaborn (>=0.8.1)
Requires-Dist: matplotlib (>=2.2.2)
